Compiled from "Test.java"
public class com.jike_time.深入拆解java虚拟机.Test {
  public com.jike_time.深入拆解java虚拟机.Test();
    Code:
       0: aload_0
       1: invokespecial #1                  // Method java/lang/Object."<init>":()V
       4: return

  public static void main(java.lang.String[]);
    Code:
       0: ldc           #2                  // String This is try
       2: astore_1
       3: getstatic     #3                  // Field java/lang/System.out:Ljava/io/PrintStream;
       6: iconst_1
       7: iconst_0
       8: idiv
       9: invokevirtual #4                  // Method java/io/PrintStream.println:(I)V
      12: ldc           #5                  // String This is finally
      14: astore_1
      15: goto          35
      18: astore_1
      19: ldc           #7                  // String This is catch
      21: astore_2
      22: ldc           #5                  // String This is finally
      24: astore_1
      25: goto          35
      28: astore_3
      29: ldc           #5                  // String This is finally
      31: astore        4
      33: aload_3
      34: athrow
      35: ldc           #8                  // String This is exit
      37: astore_1
      38: return
    Exception table:
       from    to  target type
           0    12    18   Class java/lang/Exception
           0    12    28   any
          18    22    28   any
}
